{
   "results" : [
      {
         "address_components" : [
            {
               "long_name" : "7600",
               "short_name" : "7600",
               "types" : [ "street_number" ]
            },
            {
               "long_name" : "S.M. Wright Freeway",
               "short_name" : "S.M. Wright Fwy",
               "types" : [ "route" ]
            },
            {
               "long_name" : "Dallas",
               "short_name" : "Dallas",
               "types" : [ "locality", "political" ]
            },
            {
               "long_name" : "Dallas County",
               "short_name" : "Dallas County",
               "types" : [ "administrative_area_level_2", "political" ]
            },
            {
               "long_name" : "Texas",
               "short_name" : "TX",
               "types" : [ "administrative_area_level_1", "political" ]
            },
            {
               "long_name" : "United States",
               "short_name" : "US",
               "types" : [ "country", "political" ]
            },
            {
               "long_name" : "75216",
               "short_name" : "75216",
               "types" : [ "postal_code" ]
            }
         ],
         "formatted_address" : "7600 S.M. Wright Freeway, Dallas, TX 75216, USA",
         "geometry" : {
            "bounds" : {
               "northeast" : {
                  "lat" : 32.7200519,
                  "lng" : -96.7578802
               },
               "southwest" : {
                  "lat" : 32.7200461,
                  "lng" : -96.7578973
               }
            },
            "location" : {
               "lat" : 32.7200519,
               "lng" : -96.7578802
            },
            "location_type" : "RANGE_INTERPOLATED",
            "viewport" : {
               "northeast" : {
                  "lat" : 32.7213979802915,
                  "lng" : -96.7565397697085
               },
               "southwest" : {
                  "lat" : 32.71870001970851,
                  "lng" : -96.7592377302915
               }
            }
         },
         "place_id" : "Ei83NjAwIFMuTS4gV3JpZ2h0IEZyZWV3YXksIERhbGxhcywgVFggNzUyMTYsIFVTQQ",
         "types" : [ "street_address" ]
      }
   ],
   "status" : "OK"
}
