{
   "results" : [
      {
         "address_components" : [
            {
               "long_name" : "9830",
               "short_name" : "9830",
               "types" : [ "street_number" ]
            },
            {
               "long_name" : "Chapel Hill Road",
               "short_name" : "Chapel Hill Rd",
               "types" : [ "route" ]
            },
            {
               "long_name" : "Davenport",
               "short_name" : "Davenport",
               "types" : [ "locality", "political" ]
            },
            {
               "long_name" : "Buffalo",
               "short_name" : "Buffalo",
               "types" : [ "administrative_area_level_3", "political" ]
            },
            {
               "long_name" : "Scott County",
               "short_name" : "Scott County",
               "types" : [ "administrative_area_level_2", "political" ]
            },
            {
               "long_name" : "Iowa",
               "short_name" : "IA",
               "types" : [ "administrative_area_level_1", "political" ]
            },
            {
               "long_name" : "United States",
               "short_name" : "US",
               "types" : [ "country", "political" ]
            },
            {
               "long_name" : "52804",
               "short_name" : "52804",
               "types" : [ "postal_code" ]
            },
            {
               "long_name" : "8832",
               "short_name" : "8832",
               "types" : [ "postal_code_suffix" ]
            }
         ],
         "formatted_address" : "9830 Chapel Hill Road, Davenport, IA 52804, USA",
         "geometry" : {
            "bounds" : {
               "northeast" : {
                  "lat" : 41.4942809,
                  "lng" : -90.7108583
               },
               "southwest" : {
                  "lat" : 41.494267,
                  "lng" : -90.7108583
               }
            },
            "location" : {
               "lat" : 41.4942809,
               "lng" : -90.7108583
            },
            "location_type" : "RANGE_INTERPOLATED",
            "viewport" : {
               "northeast" : {
                  "lat" : 41.4956229302915,
                  "lng" : -90.70950931970849
               },
               "southwest" : {
                  "lat" : 41.4929249697085,
                  "lng" : -90.71220728029149
               }
            }
         },
         "partial_match" : true,
         "place_id" : "Ei85ODMwIENoYXBlbCBIaWxsIFJvYWQsIERhdmVucG9ydCwgSUEgNTI4MDQsIFVTQQ",
         "types" : [ "street_address" ]
      },
      {
         "address_components" : [
            {
               "long_name" : "9830",
               "short_name" : "9830",
               "types" : [ "street_number" ]
            },
            {
               "long_name" : "Chapel Creek Boulevard",
               "short_name" : "Chapel Creek Blvd",
               "types" : [ "route" ]
            },
            {
               "long_name" : "Chapel Creek",
               "short_name" : "Chapel Creek",
               "types" : [ "neighborhood", "political" ]
            },
            {
               "long_name" : "Fort Worth",
               "short_name" : "Fort Worth",
               "types" : [ "locality", "political" ]
            },
            {
               "long_name" : "Tarrant County",
               "short_name" : "Tarrant County",
               "types" : [ "administrative_area_level_2", "political" ]
            },
            {
               "long_name" : "Texas",
               "short_name" : "TX",
               "types" : [ "administrative_area_level_1", "political" ]
            },
            {
               "long_name" : "United States",
               "short_name" : "US",
               "types" : [ "country", "political" ]
            },
            {
               "long_name" : "76108",
               "short_name" : "76108",
               "types" : [ "postal_code" ]
            }
         ],
         "formatted_address" : "9830 Chapel Creek Boulevard, Fort Worth, TX 76108, USA",
         "geometry" : {
            "bounds" : {
               "northeast" : {
                  "lat" : 32.7386252,
                  "lng" : -97.50361649999999
               },
               "southwest" : {
                  "lat" : 32.7386236,
                  "lng" : -97.5036348
               }
            },
            "location" : {
               "lat" : 32.7386236,
               "lng" : -97.50361649999999
            },
            "location_type" : "RANGE_INTERPOLATED",
            "viewport" : {
               "northeast" : {
                  "lat" : 32.7399733802915,
                  "lng" : -97.50227666970849
               },
               "southwest" : {
                  "lat" : 32.7372754197085,
                  "lng" : -97.5049746302915
               }
            }
         },
         "partial_match" : true,
         "place_id" : "EjY5ODMwIENoYXBlbCBDcmVlayBCb3VsZXZhcmQsIEZvcnQgV29ydGgsIFRYIDc2MTA4LCBVU0E",
         "types" : [ "street_address" ]
      },
      {
         "address_components" : [
            {
               "long_name" : "9830",
               "short_name" : "9830",
               "types" : [ "street_number" ]
            },
            {
               "long_name" : "Chapel Hill Road",
               "short_name" : "Chapel Hill Rd",
               "types" : [ "route" ]
            },
            {
               "long_name" : "Lake Stevens",
               "short_name" : "Lake Stevens",
               "types" : [ "locality", "political" ]
            },
            {
               "long_name" : "Snohomish County",
               "short_name" : "Snohomish County",
               "types" : [ "administrative_area_level_2", "political" ]
            },
            {
               "long_name" : "Washington",
               "short_name" : "WA",
               "types" : [ "administrative_area_level_1", "political" ]
            },
            {
               "long_name" : "United States",
               "short_name" : "US",
               "types" : [ "country", "political" ]
            },
            {
               "long_name" : "98258",
               "short_name" : "98258",
               "types" : [ "postal_code" ]
            }
         ],
         "formatted_address" : "9830 Chapel Hill Road, Lake Stevens, WA 98258, USA",
         "geometry" : {
            "bounds" : {
               "northeast" : {
                  "lat" : 47.9957729,
                  "lng" : -122.0991009
               },
               "southwest" : {
                  "lat" : 47.9957605,
                  "lng" : -122.0991012
               }
            },
            "location" : {
               "lat" : 47.9957605,
               "lng" : -122.0991009
            },
            "location_type" : "RANGE_INTERPOLATED",
            "viewport" : {
               "northeast" : {
                  "lat" : 47.99711568029149,
                  "lng" : -122.0977520697085
               },
               "southwest" : {
                  "lat" : 47.99441771970849,
                  "lng" : -122.1004500302915
               }
            }
         },
         "partial_match" : true,
         "place_id" : "EjI5ODMwIENoYXBlbCBIaWxsIFJvYWQsIExha2UgU3RldmVucywgV0EgOTgyNTgsIFVTQQ",
         "types" : [ "street_address" ]
      },
      {
         "address_components" : [
            {
               "long_name" : "9830",
               "short_name" : "9830",
               "types" : [ "street_number" ]
            },
            {
               "long_name" : "Chapel Hill Road",
               "short_name" : "Chapel Hill Rd",
               "types" : [ "route" ]
            },
            {
               "long_name" : "Louisville",
               "short_name" : "Louisville",
               "types" : [ "locality", "political" ]
            },
            {
               "long_name" : "Jefferson County",
               "short_name" : "Jefferson County",
               "types" : [ "administrative_area_level_2", "political" ]
            },
            {
               "long_name" : "Kentucky",
               "short_name" : "KY",
               "types" : [ "administrative_area_level_1", "political" ]
            },
            {
               "long_name" : "United States",
               "short_name" : "US",
               "types" : [ "country", "political" ]
            },
            {
               "long_name" : "40229",
               "short_name" : "40229",
               "types" : [ "postal_code" ]
            },
            {
               "long_name" : "1205",
               "short_name" : "1205",
               "types" : [ "postal_code_suffix" ]
            }
         ],
         "formatted_address" : "9830 Chapel Hill Road, Louisville, KY 40229, USA",
         "geometry" : {
            "bounds" : {
               "northeast" : {
                  "lat" : 38.104805,
                  "lng" : -85.66687349999999
               },
               "southwest" : {
                  "lat" : 38.1048045,
                  "lng" : -85.6668919
               }
            },
            "location" : {
               "lat" : 38.104805,
               "lng" : -85.6668919
            },
            "location_type" : "RANGE_INTERPOLATED",
            "viewport" : {
               "northeast" : {
                  "lat" : 38.1061537302915,
                  "lng" : -85.66553371970848
               },
               "southwest" : {
                  "lat" : 38.1034557697085,
                  "lng" : -85.6682316802915
               }
            }
         },
         "partial_match" : true,
         "place_id" : "EjA5ODMwIENoYXBlbCBIaWxsIFJvYWQsIExvdWlzdmlsbGUsIEtZIDQwMjI5LCBVU0E",
         "types" : [ "street_address" ]
      },
      {
         "address_components" : [
            {
               "long_name" : "9830",
               "short_name" : "9830",
               "types" : [ "street_number" ]
            },
            {
               "long_name" : "Chapel Creek Boulevard",
               "short_name" : "Chapel Creek Blvd",
               "types" : [ "route" ]
            },
            {
               "long_name" : "Chapel Creek",
               "short_name" : "Chapel Creek",
               "types" : [ "neighborhood", "political" ]
            },
            {
               "long_name" : "Frisco",
               "short_name" : "Frisco",
               "types" : [ "locality", "political" ]
            },
            {
               "long_name" : "Collin County",
               "short_name" : "Collin County",
               "types" : [ "administrative_area_level_2", "political" ]
            },
            {
               "long_name" : "Texas",
               "short_name" : "TX",
               "types" : [ "administrative_area_level_1", "political" ]
            },
            {
               "long_name" : "United States",
               "short_name" : "US",
               "types" : [ "country", "political" ]
            },
            {
               "long_name" : "75034",
               "short_name" : "75034",
               "types" : [ "postal_code" ]
            }
         ],
         "formatted_address" : "9830 Chapel Creek Boulevard, Frisco, TX 75034, USA",
         "geometry" : {
            "bounds" : {
               "northeast" : {
                  "lat" : 33.1339853,
                  "lng" : -96.81415349999999
               },
               "southwest" : {
                  "lat" : 33.1339775,
                  "lng" : -96.8141694
               }
            },
            "location" : {
               "lat" : 33.1339853,
               "lng" : -96.8141694
            },
            "location_type" : "RANGE_INTERPOLATED",
            "viewport" : {
               "northeast" : {
                  "lat" : 33.1353303802915,
                  "lng" : -96.81281246970849
               },
               "southwest" : {
                  "lat" : 33.1326324197085,
                  "lng" : -96.8155104302915
               }
            }
         },
         "partial_match" : true,
         "place_id" : "EjI5ODMwIENoYXBlbCBDcmVlayBCb3VsZXZhcmQsIEZyaXNjbywgVFggNzUwMzQsIFVTQQ",
         "types" : [ "street_address" ]
      },
      {
         "address_components" : [
            {
               "long_name" : "Chapel Creek Road",
               "short_name" : "Chapel Creek Rd",
               "types" : [ "route" ]
            },
            {
               "long_name" : "Ross County",
               "short_name" : "Ross County",
               "types" : [ "administrative_area_level_2", "political" ]
            },
            {
               "long_name" : "Ohio",
               "short_name" : "OH",
               "types" : [ "administrative_area_level_1", "political" ]
            },
            {
               "long_name" : "United States",
               "short_name" : "US",
               "types" : [ "country", "political" ]
            }
         ],
         "formatted_address" : "Chapel Creek Road, Ohio, USA",
         "geometry" : {
            "bounds" : {
               "northeast" : {
                  "lat" : 39.4045588,
                  "lng" : -82.850864
               },
               "southwest" : {
                  "lat" : 39.3723842,
                  "lng" : -82.88953029999999
               }
            },
            "location" : {
               "lat" : 39.388506,
               "lng" : -82.86968639999999
            },
            "location_type" : "GEOMETRIC_CENTER",
            "viewport" : {
               "northeast" : {
                  "lat" : 39.4045588,
                  "lng" : -82.850864
               },
               "southwest" : {
                  "lat" : 39.3723842,
                  "lng" : -82.88953029999999
               }
            }
         },
         "partial_match" : true,
         "place_id" : "ChIJhf_ZOfmgR4gRh3lLFwh8pWA",
         "types" : [ "route" ]
      },
      {
         "address_components" : [
            {
               "long_name" : "Chapel Creek Trail",
               "short_name" : "Chapel Creek Trail",
               "types" : [ "route" ]
            },
            {
               "long_name" : "New Albany",
               "short_name" : "New Albany",
               "types" : [ "locality", "political" ]
            },
            {
               "long_name" : "Indiana",
               "short_name" : "IN",
               "types" : [ "administrative_area_level_1", "political" ]
            },
            {
               "long_name" : "United States",
               "short_name" : "US",
               "types" : [ "country", "political" ]
            },
            {
               "long_name" : "47150",
               "short_name" : "47150",
               "types" : [ "postal_code" ]
            }
         ],
         "formatted_address" : "Chapel Creek Trail, New Albany, IN 47150, USA",
         "geometry" : {
            "bounds" : {
               "northeast" : {
                  "lat" : 38.375056,
                  "lng" : -85.783862
               },
               "southwest" : {
                  "lat" : 38.36915,
                  "lng" : -85.79818589999999
               }
            },
            "location" : {
               "lat" : 38.3713451,
               "lng" : -85.79167009999999
            },
            "location_type" : "GEOMETRIC_CENTER",
            "viewport" : {
               "northeast" : {
                  "lat" : 38.375056,
                  "lng" : -85.783862
               },
               "southwest" : {
                  "lat" : 38.36915,
                  "lng" : -85.79818589999999
               }
            }
         },
         "partial_match" : true,
         "place_id" : "ChIJp62eFrRvaYgRnlVOtBGtyLs",
         "types" : [ "route" ]
      },
      {
         "address_components" : [
            {
               "long_name" : "Chapel Creek Drive",
               "short_name" : "Chapel Creek Dr",
               "types" : [ "route" ]
            },
            {
               "long_name" : "Jackson",
               "short_name" : "Jackson",
               "types" : [ "locality", "political" ]
            },
            {
               "long_name" : "Madison County",
               "short_name" : "Madison County",
               "types" : [ "administrative_area_level_2", "political" ]
            },
            {
               "long_name" : "Tennessee",
               "short_name" : "TN",
               "types" : [ "administrative_area_level_1", "political" ]
            },
            {
               "long_name" : "United States",
               "short_name" : "US",
               "types" : [ "country", "political" ]
            },
            {
               "long_name" : "38305",
               "short_name" : "38305",
               "types" : [ "postal_code" ]
            }
         ],
         "formatted_address" : "Chapel Creek Drive, Jackson, TN 38305, USA",
         "geometry" : {
            "bounds" : {
               "northeast" : {
                  "lat" : 35.6905072,
                  "lng" : -88.836643
               },
               "southwest" : {
                  "lat" : 35.68735,
                  "lng" : -88.84132799999999
               }
            },
            "location" : {
               "lat" : 35.6890548,
               "lng" : -88.839325
            },
            "location_type" : "GEOMETRIC_CENTER",
            "viewport" : {
               "northeast" : {
                  "lat" : 35.6905072,
                  "lng" : -88.836643
               },
               "southwest" : {
                  "lat" : 35.68735,
                  "lng" : -88.84132799999999
               }
            }
         },
         "partial_match" : true,
         "place_id" : "ChIJe_ohWPamfogRJ05W7sohjxU",
         "types" : [ "route" ]
      },
      {
         "address_components" : [
            {
               "long_name" : "Chapel Creek Drive",
               "short_name" : "Chapel Creek Dr",
               "types" : [ "route" ]
            },
            {
               "long_name" : "Northwest Dallas",
               "short_name" : "Northwest Dallas",
               "types" : [ "neighborhood", "political" ]
            },
            {
               "long_name" : "Dallas",
               "short_name" : "Dallas",
               "types" : [ "locality", "political" ]
            },
            {
               "long_name" : "Dallas County",
               "short_name" : "Dallas County",
               "types" : [ "administrative_area_level_2", "political" ]
            },
            {
               "long_name" : "Texas",
               "short_name" : "TX",
               "types" : [ "administrative_area_level_1", "political" ]
            },
            {
               "long_name" : "United States",
               "short_name" : "US",
               "types" : [ "country", "political" ]
            },
            {
               "long_name" : "75220",
               "short_name" : "75220",
               "types" : [ "postal_code" ]
            }
         ],
         "formatted_address" : "Chapel Creek Drive, Dallas, TX 75220, USA",
         "geometry" : {
            "bounds" : {
               "northeast" : {
                  "lat" : 32.872418,
                  "lng" : -96.86463599999999
               },
               "southwest" : {
                  "lat" : 32.870895,
                  "lng" : -96.86923329999999
               }
            },
            "location" : {
               "lat" : 32.8716947,
               "lng" : -96.86690019999999
            },
            "location_type" : "GEOMETRIC_CENTER",
            "viewport" : {
               "northeast" : {
                  "lat" : 32.8730054802915,
                  "lng" : -96.86463599999999
               },
               "southwest" : {
                  "lat" : 32.8703075197085,
                  "lng" : -96.86923329999999
               }
            }
         },
         "partial_match" : true,
         "place_id" : "ChIJxVHM3pmdToYRRn_ptA-nYjM",
         "types" : [ "route" ]
      },
      {
         "address_components" : [
            {
               "long_name" : "Chapel Creek Drive",
               "short_name" : "Chapel Creek Dr",
               "types" : [ "route" ]
            },
            {
               "long_name" : "Midlothian",
               "short_name" : "Midlothian",
               "types" : [ "locality", "political" ]
            },
            {
               "long_name" : "Ellis County",
               "short_name" : "Ellis County",
               "types" : [ "administrative_area_level_2", "political" ]
            },
            {
               "long_name" : "Texas",
               "short_name" : "TX",
               "types" : [ "administrative_area_level_1", "political" ]
            },
            {
               "long_name" : "United States",
               "short_name" : "US",
               "types" : [ "country", "political" ]
            },
            {
               "long_name" : "76065",
               "short_name" : "76065",
               "types" : [ "postal_code" ]
            }
         ],
         "formatted_address" : "Chapel Creek Drive, Midlothian, TX 76065, USA",
         "geometry" : {
            "bounds" : {
               "northeast" : {
                  "lat" : 32.4939187,
                  "lng" : -97.0034326
               },
               "southwest" : {
                  "lat" : 32.493619,
                  "lng" : -97.00914859999999
               }
            },
            "location" : {
               "lat" : 32.4938735,
               "lng" : -97.0055285
            },
            "location_type" : "GEOMETRIC_CENTER",
            "viewport" : {
               "northeast" : {
                  "lat" : 32.49511783029151,
                  "lng" : -97.0034326
               },
               "southwest" : {
                  "lat" : 32.49241986970851,
                  "lng" : -97.00914859999999
               }
            }
         },
         "partial_match" : true,
         "place_id" : "ChIJwZLFDWLzToYR22lBYd-1Vto",
         "types" : [ "route" ]
      },
      {
         "address_components" : [
            {
               "long_name" : "9830",
               "short_name" : "9830",
               "types" : [ "street_number" ]
            },
            {
               "long_name" : "Chapel Hill Road",
               "short_name" : "Chapel Hill Rd",
               "types" : [ "route" ]
            },
            {
               "long_name" : "Chapel Hill",
               "short_name" : "Chapel Hill",
               "types" : [ "locality", "political" ]
            },
            {
               "long_name" : "Williams",
               "short_name" : "Williams",
               "types" : [ "administrative_area_level_3", "political" ]
            },
            {
               "long_name" : "Chatham County",
               "short_name" : "Chatham County",
               "types" : [ "administrative_area_level_2", "political" ]
            },
            {
               "long_name" : "North Carolina",
               "short_name" : "NC",
               "types" : [ "administrative_area_level_1", "political" ]
            },
            {
               "long_name" : "United States",
               "short_name" : "US",
               "types" : [ "country", "political" ]
            },
            {
               "long_name" : "27517",
               "short_name" : "27517",
               "types" : [ "postal_code" ]
            }
         ],
         "formatted_address" : "9830 Chapel Hill Road, Chapel Hill, NC 27517, USA",
         "geometry" : {
            "bounds" : {
               "northeast" : {
                  "lat" : 35.8279552,
                  "lng" : -79.0873981
               },
               "southwest" : {
                  "lat" : 35.8279551,
                  "lng" : -79.0874165
               }
            },
            "location" : {
               "lat" : 35.8279551,
               "lng" : -79.0873981
            },
            "location_type" : "RANGE_INTERPOLATED",
            "viewport" : {
               "northeast" : {
                  "lat" : 35.8293041302915,
                  "lng" : -79.0860583197085
               },
               "southwest" : {
                  "lat" : 35.8266061697085,
                  "lng" : -79.08875628029152
               }
            }
         },
         "partial_match" : true,
         "place_id" : "EjE5ODMwIENoYXBlbCBIaWxsIFJvYWQsIENoYXBlbCBIaWxsLCBOQyAyNzUxNywgVVNB",
         "types" : [ "street_address" ]
      },
      {
         "address_components" : [
            {
               "long_name" : "9830",
               "short_name" : "9830",
               "types" : [ "street_number" ]
            },
            {
               "long_name" : "Chapel Hill Road",
               "short_name" : "Chapel Hill Rd",
               "types" : [ "route" ]
            },
            {
               "long_name" : "Morrisville",
               "short_name" : "Morrisville",
               "types" : [ "locality", "political" ]
            },
            {
               "long_name" : "Cedar Fork",
               "short_name" : "Cedar Fork",
               "types" : [ "administrative_area_level_3", "political" ]
            },
            {
               "long_name" : "Wake County",
               "short_name" : "Wake County",
               "types" : [ "administrative_area_level_2", "political" ]
            },
            {
               "long_name" : "North Carolina",
               "short_name" : "NC",
               "types" : [ "administrative_area_level_1", "political" ]
            },
            {
               "long_name" : "United States",
               "short_name" : "US",
               "types" : [ "country", "political" ]
            },
            {
               "long_name" : "27560",
               "short_name" : "27560",
               "types" : [ "postal_code" ]
            }
         ],
         "formatted_address" : "9830 Chapel Hill Road, Morrisville, NC 27560, USA",
         "geometry" : {
            "bounds" : {
               "northeast" : {
                  "lat" : 35.8100808,
                  "lng" : -78.8163575
               },
               "southwest" : {
                  "lat" : 35.81007719999999,
                  "lng" : -78.8163754
               }
            },
            "location" : {
               "lat" : 35.8100808,
               "lng" : -78.8163575
            },
            "location_type" : "RANGE_INTERPOLATED",
            "viewport" : {
               "northeast" : {
                  "lat" : 35.81142798029149,
                  "lng" : -78.81501746970849
               },
               "southwest" : {
                  "lat" : 35.80873001970849,
                  "lng" : -78.81771543029151
               }
            }
         },
         "partial_match" : true,
         "place_id" : "EjE5ODMwIENoYXBlbCBIaWxsIFJvYWQsIE1vcnJpc3ZpbGxlLCBOQyAyNzU2MCwgVVNB",
         "types" : [ "street_address" ]
      },
      {
         "address_components" : [
            {
               "long_name" : "Chapel Hill Circle",
               "short_name" : "Chapel Hill Cir",
               "types" : [ "route" ]
            },
            {
               "long_name" : "Joelton",
               "short_name" : "Joelton",
               "types" : [ "sublocality_level_1", "sublocality", "political" ]
            },
            {
               "long_name" : "Cheatham County",
               "short_name" : "Cheatham County",
               "types" : [ "administrative_area_level_2", "political" ]
            },
            {
               "long_name" : "Tennessee",
               "short_name" : "TN",
               "types" : [ "administrative_area_level_1", "political" ]
            },
            {
               "long_name" : "United States",
               "short_name" : "US",
               "types" : [ "country", "political" ]
            },
            {
               "long_name" : "37080",
               "short_name" : "37080",
               "types" : [ "postal_code" ]
            }
         ],
         "formatted_address" : "Chapel Hill Circle, Joelton, TN 37080, USA",
         "geometry" : {
            "bounds" : {
               "northeast" : {
                  "lat" : 36.354951,
                  "lng" : -86.9423769
               },
               "southwest" : {
                  "lat" : 36.3511584,
                  "lng" : -86.94779199999999
               }
            },
            "location" : {
               "lat" : 36.353033,
               "lng" : -86.9438028
            },
            "location_type" : "GEOMETRIC_CENTER",
            "viewport" : {
               "northeast" : {
                  "lat" : 36.354951,
                  "lng" : -86.9423769
               },
               "southwest" : {
                  "lat" : 36.3511584,
                  "lng" : -86.94779199999999
               }
            }
         },
         "partial_match" : true,
         "place_id" : "ChIJvZpGtf_2ZIgR776CMwTM_tE",
         "types" : [ "route" ]
      },
      {
         "address_components" : [
            {
               "long_name" : "9830",
               "short_name" : "9830",
               "types" : [ "street_number" ]
            },
            {
               "long_name" : "Chapel Hill Road",
               "short_name" : "Chapel Hill Rd",
               "types" : [ "route" ]
            },
            {
               "long_name" : "Douglasville",
               "short_name" : "Douglasville",
               "types" : [ "locality", "political" ]
            },
            {
               "long_name" : "Douglas County",
               "short_name" : "Douglas County",
               "types" : [ "administrative_area_level_2", "political" ]
            },
            {
               "long_name" : "Georgia",
               "short_name" : "GA",
               "types" : [ "administrative_area_level_1", "political" ]
            },
            {
               "long_name" : "United States",
               "short_name" : "US",
               "types" : [ "country", "political" ]
            },
            {
               "long_name" : "30135",
               "short_name" : "30135",
               "types" : [ "postal_code" ]
            },
            {
               "long_name" : "5061",
               "short_name" : "5061",
               "types" : [ "postal_code_suffix" ]
            }
         ],
         "formatted_address" : "9830 Chapel Hill Road, Douglasville, GA 30135, USA",
         "geometry" : {
            "bounds" : {
               "northeast" : {
                  "lat" : 33.6496072,
                  "lng" : -84.7132982
               },
               "southwest" : {
                  "lat" : 33.6495973,
                  "lng" : -84.7133123
               }
            },
            "location" : {
               "lat" : 33.6496072,
               "lng" : -84.7132982
            },
            "location_type" : "RANGE_INTERPOLATED",
            "viewport" : {
               "northeast" : {
                  "lat" : 33.6509512302915,
                  "lng" : -84.71195626970849
               },
               "southwest" : {
                  "lat" : 33.6482532697085,
                  "lng" : -84.7146542302915
               }
            }
         },
         "partial_match" : true,
         "place_id" : "EjI5ODMwIENoYXBlbCBIaWxsIFJvYWQsIERvdWdsYXN2aWxsZSwgR0EgMzAxMzUsIFVTQQ",
         "types" : [ "street_address" ]
      },
      {
         "address_components" : [
            {
               "long_name" : "9830",
               "short_name" : "9830",
               "types" : [ "street_number" ]
            },
            {
               "long_name" : "Chapel Hill Road",
               "short_name" : "Chapel Hill Rd",
               "types" : [ "route" ]
            },
            {
               "long_name" : "Crystal Springs",
               "short_name" : "Crystal Springs",
               "types" : [ "locality", "political" ]
            },
            {
               "long_name" : "Hinds County",
               "short_name" : "Hinds County",
               "types" : [ "administrative_area_level_2", "political" ]
            },
            {
               "long_name" : "Mississippi",
               "short_name" : "MS",
               "types" : [ "administrative_area_level_1", "political" ]
            },
            {
               "long_name" : "United States",
               "short_name" : "US",
               "types" : [ "country", "political" ]
            },
            {
               "long_name" : "39059",
               "short_name" : "39059",
               "types" : [ "postal_code" ]
            },
            {
               "long_name" : "9485",
               "short_name" : "9485",
               "types" : [ "postal_code_suffix" ]
            }
         ],
         "formatted_address" : "9830 Chapel Hill Road, Crystal Springs, MS 39059, USA",
         "geometry" : {
            "bounds" : {
               "northeast" : {
                  "lat" : 32.0790334,
                  "lng" : -90.4578262
               },
               "southwest" : {
                  "lat" : 32.0790177,
                  "lng" : -90.45782629999999
               }
            },
            "location" : {
               "lat" : 32.0790334,
               "lng" : -90.4578262
            },
            "location_type" : "RANGE_INTERPOLATED",
            "viewport" : {
               "northeast" : {
                  "lat" : 32.0803745302915,
                  "lng" : -90.45647726970849
               },
               "southwest" : {
                  "lat" : 32.0776765697085,
                  "lng" : -90.45917523029151
               }
            }
         },
         "partial_match" : true,
         "place_id" : "EjU5ODMwIENoYXBlbCBIaWxsIFJvYWQsIENyeXN0YWwgU3ByaW5ncywgTVMgMzkwNTksIFVTQQ",
         "types" : [ "street_address" ]
      },
      {
         "address_components" : [
            {
               "long_name" : "9830",
               "short_name" : "9830",
               "types" : [ "street_number" ]
            },
            {
               "long_name" : "Chapel Hill Road",
               "short_name" : "Chapel Hill Rd",
               "types" : [ "route" ]
            },
            {
               "long_name" : "Decatur",
               "short_name" : "Decatur",
               "types" : [ "locality", "political" ]
            },
            {
               "long_name" : "Newton County",
               "short_name" : "Newton County",
               "types" : [ "administrative_area_level_2", "political" ]
            },
            {
               "long_name" : "Mississippi",
               "short_name" : "MS",
               "types" : [ "administrative_area_level_1", "political" ]
            },
            {
               "long_name" : "United States",
               "short_name" : "US",
               "types" : [ "country", "political" ]
            },
            {
               "long_name" : "39327",
               "short_name" : "39327",
               "types" : [ "postal_code" ]
            },
            {
               "long_name" : "9263",
               "short_name" : "9263",
               "types" : [ "postal_code_suffix" ]
            }
         ],
         "formatted_address" : "9830 Chapel Hill Road, Decatur, MS 39327, USA",
         "geometry" : {
            "bounds" : {
               "northeast" : {
                  "lat" : 32.4206474,
                  "lng" : -89.0188424
               },
               "southwest" : {
                  "lat" : 32.4206394,
                  "lng" : -89.0188582
               }
            },
            "location" : {
               "lat" : 32.4206474,
               "lng" : -89.0188582
            },
            "location_type" : "RANGE_INTERPOLATED",
            "viewport" : {
               "northeast" : {
                  "lat" : 32.42199238029149,
                  "lng" : -89.01750131970849
               },
               "southwest" : {
                  "lat" : 32.4192944197085,
                  "lng" : -89.02019928029151
               }
            }
         },
         "partial_match" : true,
         "place_id" : "Ei05ODMwIENoYXBlbCBIaWxsIFJvYWQsIERlY2F0dXIsIE1TIDM5MzI3LCBVU0E",
         "types" : [ "street_address" ]
      },
      {
         "address_components" : [
            {
               "long_name" : "9830",
               "short_name" : "9830",
               "types" : [ "street_number" ]
            },
            {
               "long_name" : "Chapel Hill Road",
               "short_name" : "Chapel Hill Rd",
               "types" : [ "route" ]
            },
            {
               "long_name" : "Toxey",
               "short_name" : "Toxey",
               "types" : [ "locality", "political" ]
            },
            {
               "long_name" : "Choctaw County",
               "short_name" : "Choctaw County",
               "types" : [ "administrative_area_level_2", "political" ]
            },
            {
               "long_name" : "Alabama",
               "short_name" : "AL",
               "types" : [ "administrative_area_level_1", "political" ]
            },
            {
               "long_name" : "United States",
               "short_name" : "US",
               "types" : [ "country", "political" ]
            },
            {
               "long_name" : "36921",
               "short_name" : "36921",
               "types" : [ "postal_code" ]
            },
            {
               "long_name" : "2063",
               "short_name" : "2063",
               "types" : [ "postal_code_suffix" ]
            }
         ],
         "formatted_address" : "9830 Chapel Hill Road, Toxey, AL 36921, USA",
         "geometry" : {
            "bounds" : {
               "northeast" : {
                  "lat" : 31.9126936,
                  "lng" : -88.30763209999999
               },
               "southwest" : {
                  "lat" : 31.9126779,
                  "lng" : -88.3076327
               }
            },
            "location" : {
               "lat" : 31.9126936,
               "lng" : -88.3076327
            },
            "location_type" : "RANGE_INTERPOLATED",
            "viewport" : {
               "northeast" : {
                  "lat" : 31.9140347302915,
                  "lng" : -88.30628341970849
               },
               "southwest" : {
                  "lat" : 31.9113367697085,
                  "lng" : -88.3089813802915
               }
            }
         },
         "partial_match" : true,
         "place_id" : "Eis5ODMwIENoYXBlbCBIaWxsIFJvYWQsIFRveGV5LCBBTCAzNjkyMSwgVVNB",
         "types" : [ "street_address" ]
      },
      {
         "address_components" : [
            {
               "long_name" : "9830",
               "short_name" : "9830",
               "types" : [ "street_number" ]
            },
            {
               "long_name" : "Chapel Hill Road",
               "short_name" : "Chapel Hill Rd",
               "types" : [ "route" ]
            },
            {
               "long_name" : "Southside",
               "short_name" : "Southside",
               "types" : [ "locality", "political" ]
            },
            {
               "long_name" : "Tennessee",
               "short_name" : "TN",
               "types" : [ "administrative_area_level_1", "political" ]
            },
            {
               "long_name" : "United States",
               "short_name" : "US",
               "types" : [ "country", "political" ]
            },
            {
               "long_name" : "37171",
               "short_name" : "37171",
               "types" : [ "postal_code" ]
            }
         ],
         "formatted_address" : "9830 Chapel Hill Road, Southside, TN 37171, USA",
         "geometry" : {
            "bounds" : {
               "northeast" : {
                  "lat" : 36.3547221,
                  "lng" : -87.28006909999999
               },
               "southwest" : {
                  "lat" : 36.3547161,
                  "lng" : -87.2800859
               }
            },
            "location" : {
               "lat" : 36.3547161,
               "lng" : -87.2800859
            },
            "location_type" : "RANGE_INTERPOLATED",
            "viewport" : {
               "northeast" : {
                  "lat" : 36.35606808029149,
                  "lng" : -87.27872851970849
               },
               "southwest" : {
                  "lat" : 36.3533701197085,
                  "lng" : -87.28142648029151
               }
            }
         },
         "partial_match" : true,
         "place_id" : "Ei85ODMwIENoYXBlbCBIaWxsIFJvYWQsIFNvdXRoc2lkZSwgVE4gMzcxNzEsIFVTQQ",
         "types" : [ "street_address" ]
      },
      {
         "address_components" : [
            {
               "long_name" : "9830",
               "short_name" : "9830",
               "types" : [ "street_number" ]
            },
            {
               "long_name" : "Chapel Hill Road",
               "short_name" : "Chapel Hill Rd",
               "types" : [ "route" ]
            },
            {
               "long_name" : "Grenada County",
               "short_name" : "Grenada County",
               "types" : [ "administrative_area_level_2", "political" ]
            },
            {
               "long_name" : "Mississippi",
               "short_name" : "MS",
               "types" : [ "administrative_area_level_1", "political" ]
            },
            {
               "long_name" : "United States",
               "short_name" : "US",
               "types" : [ "country", "political" ]
            }
         ],
         "formatted_address" : "9830 Chapel Hill Road, Mississippi, USA",
         "geometry" : {
            "bounds" : {
               "northeast" : {
                  "lat" : 33.7115666,
                  "lng" : -89.5738374
               },
               "southwest" : {
                  "lat" : 33.7115516,
                  "lng" : -89.57384139999999
               }
            },
            "location" : {
               "lat" : 33.7115666,
               "lng" : -89.57384139999999
            },
            "location_type" : "RANGE_INTERPOLATED",
            "viewport" : {
               "northeast" : {
                  "lat" : 33.7129080802915,
                  "lng" : -89.57249041970849
               },
               "southwest" : {
                  "lat" : 33.7102101197085,
                  "lng" : -89.57518838029149
               }
            }
         },
         "partial_match" : true,
         "place_id" : "Eic5ODMwIENoYXBlbCBIaWxsIFJvYWQsIE1pc3Npc3NpcHBpLCBVU0E",
         "types" : [ "street_address" ]
      },
      {
         "address_components" : [
            {
               "long_name" : "9830",
               "short_name" : "9830",
               "types" : [ "street_number" ]
            },
            {
               "long_name" : "Chapel Hill Road",
               "short_name" : "Chapel Hill Rd",
               "types" : [ "route" ]
            },
            {
               "long_name" : "Marion",
               "short_name" : "Marion",
               "types" : [ "locality", "political" ]
            },
            {
               "long_name" : "Crittenden County",
               "short_name" : "Crittenden County",
               "types" : [ "administrative_area_level_2", "political" ]
            },
            {
               "long_name" : "Kentucky",
               "short_name" : "KY",
               "types" : [ "administrative_area_level_1", "political" ]
            },
            {
               "long_name" : "United States",
               "short_name" : "US",
               "types" : [ "country", "political" ]
            },
            {
               "long_name" : "42064",
               "short_name" : "42064",
               "types" : [ "postal_code" ]
            }
         ],
         "formatted_address" : "9830 Chapel Hill Road, Marion, KY 42064, USA",
         "geometry" : {
            "bounds" : {
               "northeast" : {
                  "lat" : 37.2788809,
                  "lng" : -88.09464489999999
               },
               "southwest" : {
                  "lat" : 37.2788698,
                  "lng" : -88.09465689999999
               }
            },
            "location" : {
               "lat" : 37.2788809,
               "lng" : -88.09464489999999
            },
            "location_type" : "RANGE_INTERPOLATED",
            "viewport" : {
               "northeast" : {
                  "lat" : 37.2802243302915,
                  "lng" : -88.09330191970848
               },
               "southwest" : {
                  "lat" : 37.2775263697085,
                  "lng" : -88.09599988029149
               }
            }
         },
         "partial_match" : true,
         "place_id" : "Eiw5ODMwIENoYXBlbCBIaWxsIFJvYWQsIE1hcmlvbiwgS1kgNDIwNjQsIFVTQQ",
         "types" : [ "street_address" ]
      },
      {
         "address_components" : [
            {
               "long_name" : "9830",
               "short_name" : "9830",
               "types" : [ "street_number" ]
            },
            {
               "long_name" : "Chapel Hill Street",
               "short_name" : "Chapel Hill St",
               "types" : [ "route" ]
            },
            {
               "long_name" : "Jones",
               "short_name" : "Jones",
               "types" : [ "locality", "political" ]
            },
            {
               "long_name" : "Porter",
               "short_name" : "Porter",
               "types" : [ "administrative_area_level_3", "political" ]
            },
            {
               "long_name" : "Cass County",
               "short_name" : "Cass County",
               "types" : [ "administrative_area_level_2", "political" ]
            },
            {
               "long_name" : "Michigan",
               "short_name" : "MI",
               "types" : [ "administrative_area_level_1", "political" ]
            },
            {
               "long_name" : "United States",
               "short_name" : "US",
               "types" : [ "country", "political" ]
            },
            {
               "long_name" : "49061",
               "short_name" : "49061",
               "types" : [ "postal_code" ]
            },
            {
               "long_name" : "9750",
               "short_name" : "9750",
               "types" : [ "postal_code_suffix" ]
            }
         ],
         "formatted_address" : "9830 Chapel Hill Street, Jones, MI 49061, USA",
         "geometry" : {
            "bounds" : {
               "northeast" : {
                  "lat" : 41.8094627,
                  "lng" : -85.8337607
               },
               "southwest" : {
                  "lat" : 41.8094519,
                  "lng" : -85.8337722
               }
            },
            "location" : {
               "lat" : 41.8094627,
               "lng" : -85.8337722
            },
            "location_type" : "RANGE_INTERPOLATED",
            "viewport" : {
               "northeast" : {
                  "lat" : 41.81080628029149,
                  "lng" : -85.83241746970849
               },
               "southwest" : {
                  "lat" : 41.8081083197085,
                  "lng" : -85.83511543029151
               }
            }
         },
         "partial_match" : true,
         "place_id" : "Ei05ODMwIENoYXBlbCBIaWxsIFN0cmVldCwgSm9uZXMsIE1JIDQ5MDYxLCBVU0E",
         "types" : [ "street_address" ]
      },
      {
         "address_components" : [
            {
               "long_name" : "9830",
               "short_name" : "9830",
               "types" : [ "street_number" ]
            },
            {
               "long_name" : "Chapel Hill Road",
               "short_name" : "Chapel Hill Rd",
               "types" : [ "route" ]
            },
            {
               "long_name" : "South Fulton",
               "short_name" : "South Fulton",
               "types" : [ "locality", "political" ]
            },
            {
               "long_name" : "Obion County",
               "short_name" : "Obion County",
               "types" : [ "administrative_area_level_2", "political" ]
            },
            {
               "long_name" : "Tennessee",
               "short_name" : "TN",
               "types" : [ "administrative_area_level_1", "political" ]
            },
            {
               "long_name" : "United States",
               "short_name" : "US",
               "types" : [ "country", "political" ]
            },
            {
               "long_name" : "38257",
               "short_name" : "38257",
               "types" : [ "postal_code" ]
            }
         ],
         "formatted_address" : "9830 Chapel Hill Road, South Fulton, TN 38257, USA",
         "geometry" : {
            "bounds" : {
               "northeast" : {
                  "lat" : 36.4437739,
                  "lng" : -88.8690639
               },
               "southwest" : {
                  "lat" : 36.4437591,
                  "lng" : -88.86906569999999
               }
            },
            "location" : {
               "lat" : 36.4437739,
               "lng" : -88.8690639
            },
            "location_type" : "RANGE_INTERPOLATED",
            "viewport" : {
               "northeast" : {
                  "lat" : 36.4451154802915,
                  "lng" : -88.86771581970848
               },
               "southwest" : {
                  "lat" : 36.4424175197085,
                  "lng" : -88.8704137802915
               }
            }
         },
         "partial_match" : true,
         "place_id" : "EjI5ODMwIENoYXBlbCBIaWxsIFJvYWQsIFNvdXRoIEZ1bHRvbiwgVE4gMzgyNTcsIFVTQQ",
         "types" : [ "street_address" ]
      },
      {
         "address_components" : [
            {
               "long_name" : "9830",
               "short_name" : "9830",
               "types" : [ "street_number" ]
            },
            {
               "long_name" : "Chapel Grove Road",
               "short_name" : "Chapel Grove Rd",
               "types" : [ "route" ]
            },
            {
               "long_name" : "Gastonia",
               "short_name" : "Gastonia",
               "types" : [ "locality", "political" ]
            },
            {
               "long_name" : "Gastonia",
               "short_name" : "Gastonia",
               "types" : [ "administrative_area_level_3", "political" ]
            },
            {
               "long_name" : "Gaston County",
               "short_name" : "Gaston County",
               "types" : [ "administrative_area_level_2", "political" ]
            },
            {
               "long_name" : "North Carolina",
               "short_name" : "NC",
               "types" : [ "administrative_area_level_1", "political" ]
            },
            {
               "long_name" : "United States",
               "short_name" : "US",
               "types" : [ "country", "political" ]
            },
            {
               "long_name" : "28052",
               "short_name" : "28052",
               "types" : [ "postal_code" ]
            }
         ],
         "formatted_address" : "9830 Chapel Grove Road, Gastonia, NC 28052, USA",
         "geometry" : {
            "bounds" : {
               "northeast" : {
                  "lat" : 35.2120463,
                  "lng" : -81.2435929
               },
               "southwest" : {
                  "lat" : 35.2120435,
                  "lng" : -81.243611
               }
            },
            "location" : {
               "lat" : 35.2120463,
               "lng" : -81.243611
            },
            "location_type" : "RANGE_INTERPOLATED",
            "viewport" : {
               "northeast" : {
                  "lat" : 35.21339388029149,
                  "lng" : -81.2422529697085
               },
               "southwest" : {
                  "lat" : 35.2106959197085,
                  "lng" : -81.24495093029151
               }
            }
         },
         "partial_match" : true,
         "place_id" : "Ei85ODMwIENoYXBlbCBHcm92ZSBSb2FkLCBHYXN0b25pYSwgTkMgMjgwNTIsIFVTQQ",
         "types" : [ "street_address" ]
      },
      {
         "address_components" : [
            {
               "long_name" : "9830",
               "short_name" : "9830",
               "types" : [ "street_number" ]
            },
            {
               "long_name" : "Chapel Hill Road",
               "short_name" : "Chapel Hill Rd",
               "types" : [ "route" ]
            },
            {
               "long_name" : "Borden",
               "short_name" : "Borden",
               "types" : [ "locality", "political" ]
            },
            {
               "long_name" : "Greenville",
               "short_name" : "Greenville",
               "types" : [ "administrative_area_level_3", "political" ]
            },
            {
               "long_name" : "Floyd County",
               "short_name" : "Floyd County",
               "types" : [ "administrative_area_level_2", "political" ]
            },
            {
               "long_name" : "Indiana",
               "short_name" : "IN",
               "types" : [ "administrative_area_level_1", "political" ]
            },
            {
               "long_name" : "United States",
               "short_name" : "US",
               "types" : [ "country", "political" ]
            },
            {
               "long_name" : "47106",
               "short_name" : "47106",
               "types" : [ "postal_code" ]
            },
            {
               "long_name" : "9111",
               "short_name" : "9111",
               "types" : [ "postal_code_suffix" ]
            }
         ],
         "formatted_address" : "9830 Chapel Hill Road, Borden, IN 47106, USA",
         "geometry" : {
            "bounds" : {
               "northeast" : {
                  "lat" : 38.397687,
                  "lng" : -85.9667199
               },
               "southwest" : {
                  "lat" : 38.3976728,
                  "lng" : -85.9667237
               }
            },
            "location" : {
               "lat" : 38.397687,
               "lng" : -85.9667199
            },
            "location_type" : "RANGE_INTERPOLATED",
            "viewport" : {
               "northeast" : {
                  "lat" : 38.3990288802915,
                  "lng" : -85.96537281970849
               },
               "southwest" : {
                  "lat" : 38.3963309197085,
                  "lng" : -85.96807078029151
               }
            }
         },
         "partial_match" : true,
         "place_id" : "Eiw5ODMwIENoYXBlbCBIaWxsIFJvYWQsIEJvcmRlbiwgSU4gNDcxMDYsIFVTQQ",
         "types" : [ "street_address" ]
      },
      {
         "address_components" : [
            {
               "long_name" : "9830",
               "short_name" : "9830",
               "types" : [ "street_number" ]
            },
            {
               "long_name" : "Chapel Hill Road",
               "short_name" : "Chapel Hill Rd",
               "types" : [ "route" ]
            },
            {
               "long_name" : "Sullivan",
               "short_name" : "Sullivan",
               "types" : [ "locality", "political" ]
            },
            {
               "long_name" : "Meramec",
               "short_name" : "Meramec",
               "types" : [ "administrative_area_level_3", "political" ]
            },
            {
               "long_name" : "Franklin County",
               "short_name" : "Franklin County",
               "types" : [ "administrative_area_level_2", "political" ]
            },
            {
               "long_name" : "Missouri",
               "short_name" : "MO",
               "types" : [ "administrative_area_level_1", "political" ]
            },
            {
               "long_name" : "United States",
               "short_name" : "US",
               "types" : [ "country", "political" ]
            },
            {
               "long_name" : "63080",
               "short_name" : "63080",
               "types" : [ "postal_code" ]
            }
         ],
         "formatted_address" : "9830 Chapel Hill Road, Sullivan, MO 63080, USA",
         "geometry" : {
            "bounds" : {
               "northeast" : {
                  "lat" : 38.21992789999999,
                  "lng" : -90.97287899999999
               },
               "southwest" : {
                  "lat" : 38.2199266,
                  "lng" : -90.9728973
               }
            },
            "location" : {
               "lat" : 38.21992789999999,
               "lng" : -90.97287899999999
            },
            "location_type" : "RANGE_INTERPOLATED",
            "viewport" : {
               "northeast" : {
                  "lat" : 38.2212762302915,
                  "lng" : -90.97153916970849
               },
               "southwest" : {
                  "lat" : 38.2185782697085,
                  "lng" : -90.9742371302915
               }
            }
         },
         "partial_match" : true,
         "place_id" : "Ei45ODMwIENoYXBlbCBIaWxsIFJvYWQsIFN1bGxpdmFuLCBNTyA2MzA4MCwgVVNB",
         "types" : [ "street_address" ]
      },
      {
         "address_components" : [
            {
               "long_name" : "9830",
               "short_name" : "9830",
               "types" : [ "street_number" ]
            },
            {
               "long_name" : "Chapel Hill Boulevard",
               "short_name" : "Chapel Hill Blvd",
               "types" : [ "route" ]
            },
            {
               "long_name" : "Plano",
               "short_name" : "Plano",
               "types" : [ "locality", "political" ]
            },
            {
               "long_name" : "Collin County",
               "short_name" : "Collin County",
               "types" : [ "administrative_area_level_2", "political" ]
            },
            {
               "long_name" : "Texas",
               "short_name" : "TX",
               "types" : [ "administrative_area_level_1", "political" ]
            },
            {
               "long_name" : "United States",
               "short_name" : "US",
               "types" : [ "country", "political" ]
            },
            {
               "long_name" : "75093",
               "short_name" : "75093",
               "types" : [ "postal_code" ]
            }
         ],
         "formatted_address" : "9830 Chapel Hill Boulevard, Plano, TX 75093, USA",
         "geometry" : {
            "bounds" : {
               "northeast" : {
                  "lat" : 33.031877,
                  "lng" : -96.8364249
               },
               "southwest" : {
                  "lat" : 33.0318654,
                  "lng" : -96.8364371
               }
            },
            "location" : {
               "lat" : 33.031877,
               "lng" : -96.8364371
            },
            "location_type" : "RANGE_INTERPOLATED",
            "viewport" : {
               "northeast" : {
                  "lat" : 33.0332201802915,
                  "lng" : -96.83508201970848
               },
               "southwest" : {
                  "lat" : 33.0305222197085,
                  "lng" : -96.8377799802915
               }
            }
         },
         "partial_match" : true,
         "place_id" : "EjA5ODMwIENoYXBlbCBIaWxsIEJvdWxldmFyZCwgUGxhbm8sIFRYIDc1MDkzLCBVU0E",
         "types" : [ "street_address" ]
      },
      {
         "address_components" : [
            {
               "long_name" : "9830",
               "short_name" : "9830",
               "types" : [ "street_number" ]
            },
            {
               "long_name" : "Chapel Hill Boulevard",
               "short_name" : "Chapel Hill Blvd",
               "types" : [ "route" ]
            },
            {
               "long_name" : "Pasco",
               "short_name" : "Pasco",
               "types" : [ "locality", "political" ]
            },
            {
               "long_name" : "Franklin County",
               "short_name" : "Franklin County",
               "types" : [ "administrative_area_level_2", "political" ]
            },
            {
               "long_name" : "Washington",
               "short_name" : "WA",
               "types" : [ "administrative_area_level_1", "political" ]
            },
            {
               "long_name" : "United States",
               "short_name" : "US",
               "types" : [ "country", "political" ]
            },
            {
               "long_name" : "99301",
               "short_name" : "99301",
               "types" : [ "postal_code" ]
            }
         ],
         "formatted_address" : "9830 Chapel Hill Boulevard, Pasco, WA 99301, USA",
         "geometry" : {
            "bounds" : {
               "northeast" : {
                  "lat" : 46.2709035,
                  "lng" : -119.2136087
               },
               "southwest" : {
                  "lat" : 46.2708907,
                  "lng" : -119.213609
               }
            },
            "location" : {
               "lat" : 46.2709035,
               "lng" : -119.2136087
            },
            "location_type" : "RANGE_INTERPOLATED",
            "viewport" : {
               "northeast" : {
                  "lat" : 46.27224608029149,
                  "lng" : -119.2122598697085
               },
               "southwest" : {
                  "lat" : 46.2695481197085,
                  "lng" : -119.2149578302915
               }
            }
         },
         "partial_match" : true,
         "place_id" : "EjA5ODMwIENoYXBlbCBIaWxsIEJvdWxldmFyZCwgUGFzY28sIFdBIDk5MzAxLCBVU0E",
         "types" : [ "street_address" ]
      },
      {
         "address_components" : [
            {
               "long_name" : "9830",
               "short_name" : "9830",
               "types" : [ "street_number" ]
            },
            {
               "long_name" : "Chapel Branch Road",
               "short_name" : "Chapel Branch Rd",
               "types" : [ "route" ]
            },
            {
               "long_name" : "Seaford",
               "short_name" : "Seaford",
               "types" : [ "locality", "political" ]
            },
            {
               "long_name" : "Sussex County",
               "short_name" : "Sussex County",
               "types" : [ "administrative_area_level_2", "political" ]
            },
            {
               "long_name" : "Delaware",
               "short_name" : "DE",
               "types" : [ "administrative_area_level_1", "political" ]
            },
            {
               "long_name" : "United States",
               "short_name" : "US",
               "types" : [ "country", "political" ]
            },
            {
               "long_name" : "19973",
               "short_name" : "19973",
               "types" : [ "postal_code" ]
            },
            {
               "long_name" : "6921",
               "short_name" : "6921",
               "types" : [ "postal_code_suffix" ]
            }
         ],
         "formatted_address" : "9830 Chapel Branch Road, Seaford, DE 19973, USA",
         "geometry" : {
            "bounds" : {
               "northeast" : {
                  "lat" : 38.6639271,
                  "lng" : -75.6467299
               },
               "southwest" : {
                  "lat" : 38.6639265,
                  "lng" : -75.6467483
               }
            },
            "location" : {
               "lat" : 38.6639271,
               "lng" : -75.6467483
            },
            "location_type" : "RANGE_INTERPOLATED",
            "viewport" : {
               "northeast" : {
                  "lat" : 38.66527578029149,
                  "lng" : -75.64539011970849
               },
               "southwest" : {
                  "lat" : 38.6625778197085,
                  "lng" : -75.64808808029152
               }
            }
         },
         "partial_match" : true,
         "place_id" : "Ei85ODMwIENoYXBlbCBCcmFuY2ggUm9hZCwgU2VhZm9yZCwgREUgMTk5NzMsIFVTQQ",
         "types" : [ "street_address" ]
      },
      {
         "address_components" : [
            {
               "long_name" : "Chapel Hill Lane",
               "short_name" : "Chapel Hill Ln",
               "types" : [ "route" ]
            },
            {
               "long_name" : "Prospect",
               "short_name" : "Prospect",
               "types" : [ "locality", "political" ]
            },
            {
               "long_name" : "Butler County",
               "short_name" : "Butler County",
               "types" : [ "administrative_area_level_2", "political" ]
            },
            {
               "long_name" : "Pennsylvania",
               "short_name" : "PA",
               "types" : [ "administrative_area_level_1", "political" ]
            },
            {
               "long_name" : "United States",
               "short_name" : "US",
               "types" : [ "country", "political" ]
            },
            {
               "long_name" : "16052",
               "short_name" : "16052",
               "types" : [ "postal_code" ]
            }
         ],
         "formatted_address" : "Chapel Hill Lane, Prospect, PA 16052, USA",
         "geometry" : {
            "bounds" : {
               "northeast" : {
                  "lat" : 40.8839613,
                  "lng" : -80.0291953
               },
               "southwest" : {
                  "lat" : 40.8818259,
                  "lng" : -80.0444502
               }
            },
            "location" : {
               "lat" : 40.8836437,
               "lng" : -80.037441
            },
            "location_type" : "GEOMETRIC_CENTER",
            "viewport" : {
               "northeast" : {
                  "lat" : 40.8842425802915,
                  "lng" : -80.0291953
               },
               "southwest" : {
                  "lat" : 40.8815446197085,
                  "lng" : -80.0444502
               }
            }
         },
         "partial_match" : true,
         "place_id" : "ChIJVVJTdVx-M4gRqB5cLKfFnxw",
         "types" : [ "route" ]
      },
      {
         "address_components" : [
            {
               "long_name" : "Chapel Field Road",
               "short_name" : "Chapel Field Rd",
               "types" : [ "route" ]
            },
            {
               "long_name" : "Denton",
               "short_name" : "Denton",
               "types" : [ "locality", "political" ]
            },
            {
               "long_name" : "Manchester",
               "short_name" : "Manchester",
               "types" : [ "postal_town" ]
            },
            {
               "long_name" : "Greater Manchester",
               "short_name" : "Gt Man",
               "types" : [ "administrative_area_level_2", "political" ]
            },
            {
               "long_name" : "United Kingdom",
               "short_name" : "GB",
               "types" : [ "country", "political" ]
            },
            {
               "long_name" : "M34 6DN",
               "short_name" : "M34 6DN",
               "types" : [ "postal_code" ]
            }
         ],
         "formatted_address" : "Chapel Field Road, Denton, Manchester M34 6DN, UK",
         "geometry" : {
            "bounds" : {
               "northeast" : {
                  "lat" : 53.45252259999999,
                  "lng" : -2.108721
               },
               "southwest" : {
                  "lat" : 53.4515982,
                  "lng" : -2.1090968
               }
            },
            "location" : {
               "lat" : 53.45252259999999,
               "lng" : -2.1089741
            },
            "location_type" : "GEOMETRIC_CENTER",
            "viewport" : {
               "northeast" : {
                  "lat" : 53.4534093802915,
                  "lng" : -2.107559919708498
               },
               "southwest" : {
                  "lat" : 53.4507114197085,
                  "lng" : -2.110257880291502
               }
            }
         },
         "partial_match" : true,
         "place_id" : "ChIJB5YSZCy0e0gRl7Yn3zlrGwM",
         "types" : [ "route" ]
      }
   ],
   "status" : "OK"
}
